PackagePy/Server_Swagger.py
PackagePy/__init__.py
PackagePy/jwtclass.py
PackagePy/queryclass.py
lcms_swagger-0.0.3.dist-info/METADATA
lcms_swagger-0.0.3.dist-info/WHEEL
lcms_swagger-0.0.3.dist-info/top_level.txt
lcms_swagger-0.0.3.dist-info/RECORD
